{
    "boundary": {
        "boundary_info": {
            "coordinates": [
                {
                    "latitude": 50,
                    "longitude": -100,
                    "x": -11131949,
                    "y": -6446275
                }
            ],
            "name": "rectangle"
        }
    },
    "goal": {
        "coordinates": {
            "latitude": 37.229792,
            "longitude": -80.4226,
            "x": -8952602,
            "y": -4471185
        }
    },
    "obstacles": [
        {
            "obstacle_id": 0,
            "obstacle_info": {
                "coordinates": [
                    {
                        "latitude": 37.229788,
                        "longitude": -80.4228,
                        "x": -8952625,
                        "y": -4471184
                    },
                    {
                        "latitude": 37.229799,
                        "longitude": -80.4228,
                        "x": -8952625,
                        "y": -4471186
                    },
                    {
                        "latitude": 37.229799,
                        "longitude": -80.4229,
                        "x": -8952636,
                        "y": -4471186
                    },
                    {
                        "latitude": 37.229788,
                        "longitude": -80.4229,
                        "x": -8952636,
                        "y": -4471184
                    }
                ],
                "name": "rectangle"
            }
        }
    ],
    "path": {
        "coordinates": [
            {
                "latitude": 0,
                "longitude": 0
            }
        ],
        "path_cost": 1
    },
    "problem_id": 0,
    "regions": {
        "searched": [
            {
                "id": 0,
                "points": [
                    {
                        "latitude": 0,
                        "longitude": 0
                    }
                ],
                "radius": 0
            }
        ],
        "unsearched": {
            "cache": [
                {
                    "id": 0,
                    "points": [
                        {
                            "latitude": 0,
                            "longitude": 0
                        }
                    ]
                }
            ],
            "version": 0
        }
    },
    "robots": [
        {
            "coordinates": {
                "latitude": 37.229792,
                "longitude": -80.423788,
                "x": -8952735,
                "y": -4471185
            },
            "id": 0
        }
    ]
}